duc193/__init__.py
duc193/installer.py
duc193-0.1.0.dist-info/METADATA
duc193-0.1.0.dist-info/WHEEL
duc193-0.1.0.dist-info/top_level.txt
duc193-0.1.0.dist-info/RECORD
